setup.cfg
setup.py
Sympal/MailingList.py
Sympal/MailingList_Meta.py
Sympal/Subscriber.py
Sympal/Sympa.py
Sympal/Test_Sympa_MailingList.py
Sympal/__init__.py
Sympal.egg-info/PKG-INFO
Sympal.egg-info/SOURCES.txt
Sympal.egg-info/dependency_links.txt
Sympal.egg-info/requires.txt
Sympal.egg-info/top_level.txt