Metadata-Version: 1.1
Name: Sympal
Version: 0.5
Summary: Basic end user Sympa listserv management with Python requests
Home-page: https://github.com/cacampbell/Sympal
Author: Chris Campbell
Author-email: cacampbell@ucdavis.edu
License: MIT
Download-URL: https://github.com/cacampbell/Sympal/tarball/0.5
Keywords: sympa listserv requests
Platform: UNKNOWN
Classifier: Development Status :: 3 - Alpha
Classifier: Intended Audience :: Developers
Classifier: Programming Language :: Python :: 3
Classifier: Programming Language :: Python :: 3.4
Classifier: Programming Language :: Python :: 3.5
